phovea_data_hdf/__init__.py
phovea_data_hdf/bytes_to_string_encoder.py
phovea_data_hdf/calexport2hdf.py
phovea_data_hdf/config.json
phovea_data_hdf/hdf.py
phovea_data_hdf/json_encoder.py
phovea_data_hdf-8.0.0.dist-info/LICENSE
phovea_data_hdf-8.0.0.dist-info/METADATA
phovea_data_hdf-8.0.0.dist-info/WHEEL
phovea_data_hdf-8.0.0.dist-info/entry_points.txt
phovea_data_hdf-8.0.0.dist-info/top_level.txt
phovea_data_hdf-8.0.0.dist-info/RECORD
